reapit_cdk/entra_id_application/__init__.py
reapit_cdk/entra_id_application/py.typed
reapit_cdk/entra_id_application/_jsii/__init__.py
reapit_cdk/entra_id_application/_jsii/entra-id-application@0.1.0.jsii.tgz
reapit_cdk.entra_id_application-0.1.0.data/scripts/0
reapit_cdk.entra_id_application-0.1.0.data/scripts/1
reapit_cdk.entra_id_application-0.1.0.data/scripts/10
reapit_cdk.entra_id_application-0.1.0.data/scripts/11
reapit_cdk.entra_id_application-0.1.0.data/scripts/12
reapit_cdk.entra_id_application-0.1.0.data/scripts/13
reapit_cdk.entra_id_application-0.1.0.data/scripts/14
reapit_cdk.entra_id_application-0.1.0.data/scripts/2
reapit_cdk.entra_id_application-0.1.0.data/scripts/3
reapit_cdk.entra_id_application-0.1.0.data/scripts/4
reapit_cdk.entra_id_application-0.1.0.data/scripts/5
reapit_cdk.entra_id_application-0.1.0.data/scripts/6
reapit_cdk.entra_id_application-0.1.0.data/scripts/7
reapit_cdk.entra_id_application-0.1.0.data/scripts/8
reapit_cdk.entra_id_application-0.1.0.data/scripts/9
reapit_cdk.entra_id_application-0.1.0.dist-info/LICENSE
reapit_cdk.entra_id_application-0.1.0.dist-info/METADATA
reapit_cdk.entra_id_application-0.1.0.dist-info/WHEEL
reapit_cdk.entra_id_application-0.1.0.dist-info/top_level.txt
reapit_cdk.entra_id_application-0.1.0.dist-info/RECORD
